{
  "updated_at": "2026-01-29T06:43:05.049616+00:00",
  "organizer_id": "1961144653483",
  "count": 4,
  "events": [
    {
      "id": "1977510621502",
      "name": "NGNH Regulations & Compliance Working Group - Session 4",
      "summary": "Session 4: Compliance Conflicts and Mandated Templates",
      "description": "Session 4: Compliance Conflicts and Mandated Templates",
      "url": "https://www.eventbrite.co.uk/e/ngnh-regulations-compliance-working-group-session-4-tickets-1977510621502",
      "start": "2026-02-04T13:00:00Z",
      "end": "2026-02-04T13:55:00Z",
      "location": "Online",
      "is_online": true,
      "logo_url": "https://img.evbuc.com/https%3A%2F%2Fcdn.evbuc.com%2Fimages%2F1122070603%2F238270579960%2F1%2Foriginal.20250912-092553?h=200&w=450&auto=format%2Ccompress&q=75&sharp=10&s=2d90626a08279f846639b1d4c86d2d55",
      "capacity": 35,
      "is_free": true,
      "is_sold_out": false,
      "has_available_tickets": true
    },
    {
      "id": "1976875056510",
      "name": "Next Gen Healthcare Energy & Sustainability Working Group - Session 2",
      "summary": "We’re excited to continue our NGHN E&S Working Group, uniting early-career professionals across healthcare construction and sustainability.",
      "description": "We’re excited to continue our NGHN E&S Working Group, uniting early-career professionals across healthcare construction and sustainability.",
      "url": "https://www.eventbrite.co.uk/e/next-gen-healthcare-energy-sustainability-working-group-session-2-tickets-1976875056510",
      "start": "2026-02-11T13:00:00Z",
      "end": "2026-02-11T13:45:00Z",
      "location": "Online",
      "is_online": true,
      "logo_url": "https://img.evbuc.com/https%3A%2F%2Fcdn.evbuc.com%2Fimages%2F1122070603%2F238270579960%2F1%2Foriginal.20250912-092553?h=200&w=450&auto=format%2Ccompress&q=75&sharp=10&s=2d90626a08279f846639b1d4c86d2d55",
      "capacity": 40,
      "is_free": true,
      "is_sold_out": false,
      "has_available_tickets": true
    },
    {
      "id": "1980852361737",
      "name": "Next Gen Healthcare Network: Coffee Catch-Up - Birmingham",
      "summary": "Join the NGHN to discuss the hot topics of the healthcare sector at our informal coffee and catch up!",
      "description": "Join the NGHN to discuss the hot topics of the healthcare sector at our informal coffee and catch up!",
      "url": "https://www.eventbrite.co.uk/e/next-gen-healthcare-network-coffee-catch-up-birmingham-tickets-1980852361737",
      "start": "2026-02-17T08:00:00Z",
      "end": "2026-02-17T09:30:00Z",
      "location": "Birmingham, England",
      "is_online": false,
      "logo_url": "https://img.evbuc.com/https%3A%2F%2Fcdn.evbuc.com%2Fimages%2F1175222802%2F238270579960%2F1%2Foriginal.20260119-090848?h=200&w=450&auto=format%2Ccompress&q=75&sharp=10&rect=40%2C0%2C842%2C421&s=0a558fae219f341fe5c18ef59285314a",
      "capacity": 40,
      "is_free": true,
      "is_sold_out": false,
      "has_available_tickets": true
    },
    {
      "id": "1980851736868",
      "name": "Next Gen Healthcare Network: Coffee Catch-Up - Nottingham",
      "summary": "Join the NGHN to discuss the hot topics of the healthcare sector at our informal coffee and catch up!",
      "description": "Join the NGHN to discuss the hot topics of the healthcare sector at our informal coffee and catch up!",
      "url": "https://www.eventbrite.co.uk/e/next-gen-healthcare-network-coffee-catch-up-nottingham-tickets-1980851736868",
      "start": "2026-02-24T08:00:00Z",
      "end": "2026-02-24T09:30:00Z",
      "location": "Nottingham, England",
      "is_online": false,
      "logo_url": "https://img.evbuc.com/https%3A%2F%2Fcdn.evbuc.com%2Fimages%2F1175222802%2F238270579960%2F1%2Foriginal.20260119-090848?h=200&w=450&auto=format%2Ccompress&q=75&sharp=10&rect=40%2C0%2C842%2C421&s=0a558fae219f341fe5c18ef59285314a",
      "capacity": 40,
      "is_free": true,
      "is_sold_out": false,
      "has_available_tickets": true
    }
  ]
}